streamlit_vtkjs/__init__.py
streamlit_vtkjs/frontend/.env
streamlit_vtkjs/frontend/.prettierrc
streamlit_vtkjs/frontend/config-overrides.js
streamlit_vtkjs/frontend/package.json
streamlit_vtkjs/frontend/tsconfig.json
streamlit_vtkjs/frontend/yarn.lock
streamlit_vtkjs/frontend/build/asset-manifest.json
streamlit_vtkjs/frontend/build/bootstrap.min.css
streamlit_vtkjs/frontend/build/index.html
streamlit_vtkjs/frontend/build/precache-manifest.812684ee6f3d39d9ecede40b38e38fbb.js
streamlit_vtkjs/frontend/build/service-worker.js
streamlit_vtkjs/frontend/build/static/css/2.fc555424.chunk.css
streamlit_vtkjs/frontend/build/static/css/2.fc555424.chunk.css.map
streamlit_vtkjs/frontend/build/static/css/main.6f2db4ab.chunk.css
streamlit_vtkjs/frontend/build/static/css/main.6f2db4ab.chunk.css.map
streamlit_vtkjs/frontend/build/static/js/2.3718ef98.chunk.js
streamlit_vtkjs/frontend/build/static/js/2.3718ef98.chunk.js.LICENSE.txt
streamlit_vtkjs/frontend/build/static/js/2.3718ef98.chunk.js.map
streamlit_vtkjs/frontend/build/static/js/main.bf1079b6.chunk.js
streamlit_vtkjs/frontend/build/static/js/main.bf1079b6.chunk.js.map
streamlit_vtkjs/frontend/build/static/js/runtime-main.6eda6c42.js
streamlit_vtkjs/frontend/build/static/js/runtime-main.6eda6c42.js.map
streamlit_vtkjs/frontend/public/bootstrap.min.css
streamlit_vtkjs/frontend/public/index.html
streamlit_vtkjs/frontend/src/VTKStreamlit.css
streamlit_vtkjs/frontend/src/VTKStreamlit.tsx
streamlit_vtkjs/frontend/src/index.tsx
streamlit_vtkjs/frontend/src/react-app-env.d.ts
streamlit_vtkjs-0.3.2.dist-info/LICENSE
streamlit_vtkjs-0.3.2.dist-info/METADATA
streamlit_vtkjs-0.3.2.dist-info/WHEEL
streamlit_vtkjs-0.3.2.dist-info/top_level.txt
streamlit_vtkjs-0.3.2.dist-info/RECORD
