Metadata-Version: 2.1
Name: streamlit-vtkjs
Version: 0.3.2
Summary: vtkjs component for streamlit
Home-page: https://github.com/pollination/streamlit-vtkjs
Author: Pollination
Author-email: nicolas@ladybug.tools
License: UNKNOWN
Platform: UNKNOWN
Requires-Python: >=3.7
License-File: LICENSE
